CHANGES.txt
DEPENDENCIES.txt
README.txt
bootstrap.py
buildout.cfg
setup.py
src/ks/__init__.py
src/ks.channelsmtp.egg-info/PKG-INFO
src/ks.channelsmtp.egg-info/SOURCES.txt
src/ks.channelsmtp.egg-info/dependency_links.txt
src/ks.channelsmtp.egg-info/namespace_packages.txt
src/ks.channelsmtp.egg-info/not-zip-safe
src/ks.channelsmtp.egg-info/requires.txt
src/ks.channelsmtp.egg-info/top_level.txt
src/ks/channelsmtp/__init__.py
src/ks/channelsmtp/channelsmtp.py
src/ks/channelsmtp/configure.zcml
src/ks/channelsmtp/interfaces.py
src/ks/channelsmtp/browser/__init__.py
src/ks/channelsmtp/browser/configure.zcml
src/ks/channelsmtp/etc/ks.channelsmtp-configure.zcml