Metadata-Version: 1.0
Name: ks.channelsmtp
Version: 1.0.2
Summary: Message send utility through smtp
Home-page: http://code.keysolutionscorp.com/downloads/public/pypi/ks.channelsmtp
Author: Key Solutions Development TEAM
Author-email: ksd-team@keysolutions.ru
License: ZPL 2.1
Platform: UNKNOWN
Classifier: Intended Audience :: Developers
Classifier: License :: OSI Approved :: Zope Public License
Classifier: Programming Language :: Python
Classifier: Natural Language :: English
Classifier: Operating System :: OS Independent
Classifier: Topic :: Internet :: WWW/HTTP
Classifier: Topic :: Software Development
Classifier: Framework :: Zope3
